coreplatpy/__init__.py
coreplatpy/client.py
coreplatpy/account/__init__.py
coreplatpy/account/group_api.py
coreplatpy/account/role_api.py
coreplatpy/account/share_api.py
coreplatpy/account/user_api.py
coreplatpy/copernicus/__init__.py
coreplatpy/copernicus/copernicus.py
coreplatpy/models/__init__.py
coreplatpy/models/account_models.py
coreplatpy/models/api_models.py
coreplatpy/models/cop_models.py
coreplatpy/models/generic_models.py
coreplatpy/storage/__init__.py
coreplatpy/storage/buckets.py
coreplatpy/storage/copernicus.py
coreplatpy/storage/files.py
coreplatpy/storage/folders.py
coreplatpy/utils/__init__.py
coreplatpy/utils/helpers.py
CorePlatPy-1.1.2.dist-info/LICENSE
CorePlatPy-1.1.2.dist-info/METADATA
CorePlatPy-1.1.2.dist-info/WHEEL
CorePlatPy-1.1.2.dist-info/top_level.txt
CorePlatPy-1.1.2.dist-info/RECORD
