Metadata-Version: 2.1
Name: CorePlatPy
Version: 1.1.2
Summary: A Python client for the SLG's Core Platform
Home-page: https://github.com/PROJECT-BUILDSPACE/CorePlatPy/tree/main
Author-email: Iason Sotiropoulos <isotiropoulos@singularlogic.eu>, Athos Papanikolaou <apapanikolaou@singularlogic.eu>, Sotiris Aspragkathos <saspragkathos@singularlogic.eu>
Project-URL: Homepage, https://github.com/PROJECT-BUILDSPACE/CorePlatPy/tree/main
Project-URL: Issues, https://github.com/pypa/sampleproject/issues
Classifier: Programming Language :: Python :: 3
Classifier: License :: OSI Approved :: MIT License
Classifier: Operating System :: OS Independent
Requires-Python: >=3.8
License-File: LICENSE
Requires-Dist: pydantic>=2.7.0
Requires-Dist: requests
Requires-Dist: tqdm
Requires-Dist: PyJWT
Requires-Dist: httpx
Requires-Dist: aiofiles
